{
  "diffs": [
    {
      "file": "/Users/shoup/Documents/GitHub/JeebsAI/.git/FETCH_HEAD",
      "timestamp": 1771170997521,
      "toonString": "type: FileDiff\nfile: /Users/shoup/Documents/GitHub/JeebsAI/.git/FETCH_HEAD\ntimestamp: 1771170992648\nchanges:\n  - line: 1-1\n    removed: |\n      b85681a412f16b332c279b197a91dbd7ab0892e1\t\tbranch 'main' of https://github.com/1090mb/JeebsAI\nsummary: |\n  The file `/Users/shoup/Documents/GitHub/JeebsAI/.git/FETCH_HEAD` has had its content modified. Specifically, line 1, which previously contained the text `b85681a412f16b332c279b197a91dbd7ab0892e1\t\tbranch 'main' of https://github.com/1090mb/JeebsAI`, has been removed.\nanalysis: |\n  The file `.git/FETCH_HEAD` is a special file in Git that records the references that were fetched from a remote repository. It typically points to the commit(s) that were fetched. The change indicates that the previous fetch reference, which pointed to commit `b85681a412f16b332c279b197a91dbd7ab0892e1` on the `main` branch of the `https://github.com/1090mb/JeebsAI` repository, has been removed.\n  \n  This removal suggests that either:\n  1.  A new fetch operation has occurred, and the `FETCH_HEAD` file has been updated to reflect the new fetched reference(s). The diff only shows the removal, implying that the addition of the new reference is not captured in this specific diff.\n  2.  The repository's fetch state has been reset or altered in a way that removes this specific reference. This could happen during operations like `git fetch --prune` or if the `.git/FETCH_HEAD` file was manually edited or corrupted.\n  3.  The repository might have been reset to a state where this specific fetch reference is no longer relevant or present.\n  \n  The context provided (`branch 'main' of https://github.com/1090mb/JeebsAI`) is crucial. It tells us that the fetched reference was specifically from the `main` branch of the `JeebsAI` repository hosted on GitHub. The commit hash `b85681a412f16b332c279b197a91dbd7ab0892e1` represents a specific point in the history of that branch.\npotentialBugs:\n  - **Inconsistent Git State:** If this removal was not part of a successful and intended Git operation (e.g., a manual deletion or a failed fetch), it could lead to an inconsistent Git state. Other Git commands that rely on `FETCH_HEAD` (though less common than `ORIG_HEAD` or other refs) might behave unexpectedly.\n  - **Loss of Fetch History:** While `FETCH_HEAD` is transient, its removal without a corresponding update might indicate a problem with Git's internal state management.\nimpacts:\n  - **Git Operations:** The primary impact is on Git operations that might implicitly or explicitly use `FETCH_HEAD`. For instance, commands like `git merge FETCH_HEAD` or `git rebase FETCH_HEAD` would no longer work as intended, as the reference is gone.\n  - **CI/CD Pipelines:** If any Continuous Integration/Continuous Deployment (CI/CD) pipelines rely on the state of `FETCH_HEAD` to determine what to build or deploy, they might be affected. For example, a pipeline that automatically merges `FETCH_HEAD` into a local branch after a fetch would fail or behave incorrectly.\n  - **Developer Workflow:** Developers who might be using `FETCH_HEAD` in their local workflows (though this is less common than using explicit branch names or tags) would see their commands fail.\n  - **Repository Synchronization:** The removal signifies a change in what Git considers the \"latest fetched\" state from the remote. If this change is not accompanied by a new fetch, it could lead to a misunderstanding of the remote repository's current state.\n  - The change is a simple removal from a single line in a Git internal file. The impact is directly tied to how Git and any scripts or tools interact with this specific file. Since `FETCH_HEAD` is usually updated by `git fetch` commands, its removal typically means a new fetch has occurred or the file has been manipulated. Without seeing the *addition* that would normally accompany this removal in a standard fetch operation, it's hard to definitively say what the *new* state is, but the *old* state is now gone.\ncontextAware: true\n",
      "diff": {
        "type": "FileDiff",
        "file": "/Users/shoup/Documents/GitHub/JeebsAI/.git/FETCH_HEAD",
        "timestamp": 1771170992648,
        "changes": [
          {
            "line": "1-1",
            "added": "",
            "removed": "b85681a412f16b332c279b197a91dbd7ab0892e1\t\tbranch 'main' of https://github.com/1090mb/JeebsAI",
            "modified": ""
          }
        ],
        "contextAware": true,
        "summary": "The file `/Users/shoup/Documents/GitHub/JeebsAI/.git/FETCH_HEAD` has had its content modified. Specifically, line 1, which previously contained the text `b85681a412f16b332c279b197a91dbd7ab0892e1\t\tbranch 'main' of https://github.com/1090mb/JeebsAI`, has been removed.",
        "analysis": "The file `.git/FETCH_HEAD` is a special file in Git that records the references that were fetched from a remote repository. It typically points to the commit(s) that were fetched. The change indicates that the previous fetch reference, which pointed to commit `b85681a412f16b332c279b197a91dbd7ab0892e1` on the `main` branch of the `https://github.com/1090mb/JeebsAI` repository, has been removed.\n\nThis removal suggests that either:\n1.  A new fetch operation has occurred, and the `FETCH_HEAD` file has been updated to reflect the new fetched reference(s). The diff only shows the removal, implying that the addition of the new reference is not captured in this specific diff.\n2.  The repository's fetch state has been reset or altered in a way that removes this specific reference. This could happen during operations like `git fetch --prune` or if the `.git/FETCH_HEAD` file was manually edited or corrupted.\n3.  The repository might have been reset to a state where this specific fetch reference is no longer relevant or present.\n\nThe context provided (`branch 'main' of https://github.com/1090mb/JeebsAI`) is crucial. It tells us that the fetched reference was specifically from the `main` branch of the `JeebsAI` repository hosted on GitHub. The commit hash `b85681a412f16b332c279b197a91dbd7ab0892e1` represents a specific point in the history of that branch.",
        "potentialBugs": [
          "**Inconsistent Git State:** If this removal was not part of a successful and intended Git operation (e.g., a manual deletion or a failed fetch), it could lead to an inconsistent Git state. Other Git commands that rely on `FETCH_HEAD` (though less common than `ORIG_HEAD` or other refs) might behave unexpectedly.",
          "**Loss of Fetch History:** While `FETCH_HEAD` is transient, its removal without a corresponding update might indicate a problem with Git's internal state management."
        ],
        "impacts": [
          "**Git Operations:** The primary impact is on Git operations that might implicitly or explicitly use `FETCH_HEAD`. For instance, commands like `git merge FETCH_HEAD` or `git rebase FETCH_HEAD` would no longer work as intended, as the reference is gone.",
          "**CI/CD Pipelines:** If any Continuous Integration/Continuous Deployment (CI/CD) pipelines rely on the state of `FETCH_HEAD` to determine what to build or deploy, they might be affected. For example, a pipeline that automatically merges `FETCH_HEAD` into a local branch after a fetch would fail or behave incorrectly.",
          "**Developer Workflow:** Developers who might be using `FETCH_HEAD` in their local workflows (though this is less common than using explicit branch names or tags) would see their commands fail.",
          "**Repository Synchronization:** The removal signifies a change in what Git considers the \"latest fetched\" state from the remote. If this change is not accompanied by a new fetch, it could lead to a misunderstanding of the remote repository's current state.",
          "The change is a simple removal from a single line in a Git internal file. The impact is directly tied to how Git and any scripts or tools interact with this specific file. Since `FETCH_HEAD` is usually updated by `git fetch` commands, its removal typically means a new fetch has occurred or the file has been manipulated. Without seeing the *addition* that would normally accompany this removal in a standard fetch operation, it's hard to definitively say what the *new* state is, but the *old* state is now gone."
        ]
      },
      "summary": "The file `/Users/shoup/Documents/GitHub/JeebsAI/.git/FETCH_HEAD` has had its content modified. Specifically, line 1, which previously contained the text `b85681a412f16b332c279b197a91dbd7ab0892e1\t\tbranch 'main' of https://github.com/1090mb/JeebsAI`, has been removed.",
      "analysis": "The file `.git/FETCH_HEAD` is a special file in Git that records the references that were fetched from a remote repository. It typically points to the commit(s) that were fetched. The change indicates that the previous fetch reference, which pointed to commit `b85681a412f16b332c279b197a91dbd7ab0892e1` on the `main` branch of the `https://github.com/1090mb/JeebsAI` repository, has been removed.\n\nThis removal suggests that either:\n1.  A new fetch operation has occurred, and the `FETCH_HEAD` file has been updated to reflect the new fetched reference(s). The diff only shows the removal, implying that the addition of the new reference is not captured in this specific diff.\n2.  The repository's fetch state has been reset or altered in a way that removes this specific reference. This could happen during operations like `git fetch --prune` or if the `.git/FETCH_HEAD` file was manually edited or corrupted.\n3.  The repository might have been reset to a state where this specific fetch reference is no longer relevant or present.\n\nThe context provided (`branch 'main' of https://github.com/1090mb/JeebsAI`) is crucial. It tells us that the fetched reference was specifically from the `main` branch of the `JeebsAI` repository hosted on GitHub. The commit hash `b85681a412f16b332c279b197a91dbd7ab0892e1` represents a specific point in the history of that branch.",
      "potentialBugs": [
        "**Inconsistent Git State:** If this removal was not part of a successful and intended Git operation (e.g., a manual deletion or a failed fetch), it could lead to an inconsistent Git state. Other Git commands that rely on `FETCH_HEAD` (though less common than `ORIG_HEAD` or other refs) might behave unexpectedly.",
        "**Loss of Fetch History:** While `FETCH_HEAD` is transient, its removal without a corresponding update might indicate a problem with Git's internal state management."
      ],
      "impacts": [
        "**Git Operations:** The primary impact is on Git operations that might implicitly or explicitly use `FETCH_HEAD`. For instance, commands like `git merge FETCH_HEAD` or `git rebase FETCH_HEAD` would no longer work as intended, as the reference is gone.",
        "**CI/CD Pipelines:** If any Continuous Integration/Continuous Deployment (CI/CD) pipelines rely on the state of `FETCH_HEAD` to determine what to build or deploy, they might be affected. For example, a pipeline that automatically merges `FETCH_HEAD` into a local branch after a fetch would fail or behave incorrectly.",
        "**Developer Workflow:** Developers who might be using `FETCH_HEAD` in their local workflows (though this is less common than using explicit branch names or tags) would see their commands fail.",
        "**Repository Synchronization:** The removal signifies a change in what Git considers the \"latest fetched\" state from the remote. If this change is not accompanied by a new fetch, it could lead to a misunderstanding of the remote repository's current state.",
        "The change is a simple removal from a single line in a Git internal file. The impact is directly tied to how Git and any scripts or tools interact with this specific file. Since `FETCH_HEAD` is usually updated by `git fetch` commands, its removal typically means a new fetch has occurred or the file has been manipulated. Without seeing the *addition* that would normally accompany this removal in a standard fetch operation, it's hard to definitively say what the *new* state is, but the *old* state is now gone."
      ]
    }
  ],
  "lastUpdated": 1771170997522
}